{
  "title": "**Navigating Bali's Visa and Immigration Landscape: A Guide for Expats and Digital Nomads**",
  "content": "# **Navigating Bali's Visa and Immigration Landscape: A Guide for Expats and Digital Nomads**\n\nAre you considering making Bali your new home or work hub? Understanding the intricacies of the island's visa and immigration policies can be overwhelming, especially for those who are new to the expat scene. This guide aims to demystify the process, providing essential insights and practical advice for expats and digital nomads.\n\n**A Growing Community, Complex Regulations**\n\nBali has become a hotspot for tourists and expats alike, with its stunning natural beauty, rich culture, and laid-back lifestyle. The island's popularity has led to an influx of people seeking residency or visa extensions, creating a complex web of regulations that can be daunting to navigate. As a result, it's essential to understand the current laws and requirements to ensure a smooth transition.\n\n## **Overview of Bali's Visa Categories**\n\nBali offers various visa categories, each with its own set of requirements and benefits:\n\n*   **Tourist Visa**: For visitors who wish to stay in Indonesia for up to 30 days. This visa is ideal for short-term stays or trips.\n*   **Social Visa**: Suitable for those who want to live in Bali but don't meet the requirements for a work or investment visa. The social visa allows holders to stay in Indonesia for up to 6 months.\n*   **Work Visa**: For expats who have secured employment in Indonesia, this visa is required for full-time work.\n*   **Investment Visa**: Designed for entrepreneurs and investors, this visa requires significant investments in the country.\n\n## **Requirements and Application Process**\n\nThe application process for Bali's visas can be lengthy and complex. Here are some key requirements to keep in mind:\n\n*   **Documentation**: Typically includes a valid passport, completed visa application form, proof of payment, health insurance, and police certificate.\n*   **Interviews**: Some visas may require an interview with the Indonesian authorities.\n\n## **Key Takeaways**\n\n*   Understand the different visa categories available\n*   Familiarize yourself with the requirements for each category\n*   Allow sufficient time for the application process\n\n## **What This Means for You**\n\nAs a tourist, expat, or digital nomad, understanding Bali's visa and immigration landscape is crucial for planning your stay. If you're considering making the island your home, it's essential to research and comply with the regulations to avoid any issues.\n\n**Action Items:**\n\n*   Research the specific requirements for your chosen visa category\n*   Plan ahead and allow sufficient time for the application process\n\n## **Conclusion**\n\nNavigating Bali's visa and immigration policies can be complex, but understanding the basics is key to a smooth transition. By familiarizing yourself with the different visa categories, requirements, and application processes, you'll be better equipped to plan your stay in this beautiful island paradise.",
  "source_document": "https://thehoneycombers.com/bali/",
  "source_name": "Honeycombers Bali",
  "source_tier": 2,
  "category": "immigration",
  "created_at": "2025-10-08T03:15:28.378608",
  "word_count": 449,
  "target_audience": [
    "expats",
    "businesses"
  ],
  "urgency": "informational",
  "impact_level": "medium",
  "content_hash": "3151d6076f98b887",
  "model_used": "llama3.2:3b"
}