{
  "Wajib Pajak": "Tax subject - individual or entity liable for taxation (WNI and WNA)",
  "Orang Pribadi": "Individual person (can be WNI or WNA)",
  "Badan": "Legal entity/Corporation (PT Lokal or PT PMA)",
  "NPWP": "Nomor Pokok Wajib Pajak - Tax Identification Number (required for WNI and WNA taxpayers)",
  "PPh": "Pajak Penghasilan - Income Tax",
  "PPN": "Pajak Pertambahan Nilai - Value Added Tax (11% standard rate)",
  "PPnBM": "Pajak Penjualan atas Barang Mewah - Luxury Goods Sales Tax",
  "SPT": "Surat Pemberitahuan - Tax Return (annual filing requirement)",
  "KUP": "Ketentuan Umum dan Tata Cara Perpajakan - General Tax Provisions",
  "PT PMA": "Perseroan Terbatas Penanaman Modal Asing - Foreign Investment Company",
  "PT Lokal": "Local Indonesian company (majority WNI ownership)",
  "WNI": "Warga Negara Indonesia - Indonesian Citizen",
  "WNA": "Warga Negara Asing - Foreign National/Expatriate",
  "BUT": "Bentuk Usaha Tetap - Permanent Establishment",
  "Dalam Negeri": "Domestic/Resident (for tax purposes)",
  "Luar Negeri": "Foreign/Non-resident (for tax purposes)",
  "Penghasilan Kena Pajak": "Taxable Income",
  "PTKP": "Penghasilan Tidak Kena Pajak - Non-Taxable Income Threshold",
  "DJP": "Direktorat Jenderal Pajak - Directorate General of Taxation",
  "Pajak Karbon": "Carbon Tax (new in UU 7/2021)",
  "Program Pengungkapan Sukarela": "Voluntary Disclosure Program (tax amnesty)",
  "Sanksi Administrasi": "Administrative penalties (fines, interest)",
  "Sanksi Pidana": "Criminal penalties (imprisonment)",
  "Dividen": "Dividends (10% final tax)",
  "Bunga": "Interest income",
  "Royalti": "Royalty income",
  "Perseroan Terbuka": "Publicly listed company"
}
