{
  "url": "https://www.bps.go.id/",
  "source_name": "BPS Statistics Indonesia",
  "tier": 1,
  "category": "business_setup",
  "title": "Badan Pusat Statistik Indonesia",
  "description": null,
  "content": "Badan Pusat Statistik Indonesia\nBadan Pusat Statistik[![Badan Pusat Statistik](https://www.bps.go.id/_next/image?url=%2Fassets%2Flogo-bps.png&w=3840&q=75)](https://www.bps.go.id/id)\n##### [Badan Pusat Statistik](https://www.bps.go.id/id)\nOpen Menu\n[\n  * Beranda](https://www.bps.go.id/id)[\n  * Rencana Terbit](https://www.bps.go.id/id/arc)\n  * Produk\n[\n  * Layanan](https://pst.bps.go.id/)\n  * Informasi Publik\n  * ![Indonesia](https://www.bps.go.id/assets/icons/flag-icons-id.svg)\n\n\nTabel Publikasi Indikator Ekonomi telah tersedia dalam bentuk Tabel Statistik yang dapat diakses pada Menu **Produk > Direktori**. Klik [disini](https://direktori.web.bps.go.id/metabase.php?id=561&utm_source=website&utm_medium=runningtext&utm_campaign=indikator_ekonomi) untuk mengakses laman tersebut.\n![Background Image](https://www.bps.go.id/_next/image?url=%2F_next%2Fstatic%2Fmedia%2Fbg-scenery.c33dbfb6.png&w=3840&q=75)\n# Penyedia Data Statistik Berkualitas  \n\n### Informasi Terbaru\n  * [Berita Resmi Statistik](https://www.bps.go.id/id)\n  * [Tabel Statistik](https://www.bps.go.id/id)\n  * [Publikasi](https://www.bps.go.id/id)\n  * [Infografik](https://www.bps.go.id/id)\n\n[Lihat Semua BRS ](https://www.bps.go.id/id/pressrelease)\n### Video Badan Pusat Statistik\n![\\[Company Profile\\] - Badan Pusat Statistik, Mencerdaskan Bangsa dengan Data](https://www.bps.go.id/_next/image?url=https%3A%2F%2Fi.ytimg.com%2Fvi%2Fq9BYxUJ-4z4%2Fmaxresdefault.jpg&w=256&q=75)\n[Company Profile] - Badan Pusat Statistik, Mencerdaskan Bangsa dengan Data\n![\\[Videografis\\] Sistem Informasi Layanan Statistik BPS](https://www.bps.go.id/_next/image?url=https%3A%2F%2Fi.ytimg.com%2Fvi%2FN9cpMc7DctY%2Fmaxresdefault.jpg&w=256&q=75)\n[Videografis] Sistem Informasi Layanan Statistik BPS\n![Sekilas PPID BPS](https://www.bps.go.id/_next/image?url=https%3A%2F%2Fi.ytimg.com%2Fvi%2F40SfLIL7dos%2Fmaxresdefault.jpg&w=256&q=75)\nSekilas PPID BPS\n![Manfaat Data BPS](https://www.bps.go.id/_next/image?url=https%3A%2F%2Fi.ytimg.com%2Fvi%2Fqr6mQ29qdpA%2Fmaxresdefault.jpg&w=256&q=75)\nManfaat Data BPS\n### Dapatkan Data Statistik Lebih Mudah\n  * [Allstat BPS](https://www.bps.go.id/id)\n  * [Website Sensus](https://www.bps.go.id/id)\n\n\n![Allstats BPS](https://www.bps.go.id/_next/image?url=%2Fassets%2Fimages%2Fallstats.png&w=3840&q=75)\n## Akses Statistik Indonesia, Dimanapun, Kapanpun.\nUnduh aplikasi AllStats BPS untuk dapatkan kemudahan akses data BPS seperti: Statistik di sekitarmu, Indikator Strategis, Publikasi Nasional sampai daerah, Tabel Dinamis, dan masih banyak lagi.\n[![Get it on Google Play](https://www.bps.go.id/_next/image?url=%2F_next%2Fstatic%2Fmedia%2Fgoogleplay.41b50fdf.png&w=1200&q=75)](https://play.google.com/store/apps/details?id=id.go.bps.allstats)[![Download on the App Store](https://www.bps.go.id/_next/image?url=%2F_next%2Fstatic%2Fmedia%2Fappstore.52f3052e.webp&w=750&q=75)](https://apps.apple.com/id/app/allstats-bps/id1495703496)\n### Layanan Lainnya\n[![](https://www.bps.go.id/assets/icons/webapi.svg) WebAPI BPS](https://webapi.bps.go.id/developer)[![](https://www.bps.go.id/assets/icons/indah.svg) INDAH](https://indah.bps.go.id)[![](https://www.bps.go.id/assets/icons/geoportal.svg) API Geoportal](https://sig.bps.go.id)[![](https://www.bps.go.id/assets/icons/kbli-kbki.svg) KBLI KBKI](https://klasifikasi.web.bps.go.id/)\n![Badan Pusat Statistik](https://www.bps.go.id/_next/image?url=%2Fassets%2Flogo-bps.png&w=256&q=75)\nBadan Pusat Statistik\nBadan Pusat Statistik(BPS - Statistics Indonesia)\nJl. Dr. Sutomo 6-8\nJakarta 10710 Indonesia\nTelp (62-21) 3841195; 3842508; 3810291\nFaks (62-21) 3857046\nMailbox : bpshq@bps.go.id\n![logo_footer](https://www.bps.go.id/_next/image?url=https%3A%2F%2Fweb-api.bps.go.id%2Fcover.php%3Ff%3Dl4w%2FI%2BoGWH3sEmz5glAYGFpIZHRJNGdWNDQ1V0pTeGEwVURMcWhCVmRCRjlzSEpXRW8rVDBUaWgwdWxnOGtyaEFRM3pWdERsc1V2TjE2UHlPajJUY09IWDIxM1RKNlJiTW5BN013PT0%3D&w=3840&q=75)\n[Manual](https://manual-website-bps.readthedocs.io)[S&K](https://www.bps.go.id/id/term-of-use)[Daftar Tautan](https://www.bps.go.id/id/tautan)\nTentang Kami\n  * [Profil BPS](https://ppid.bps.go.id/app/konten/0000/Profil-BPS.html)\n  * [PPID](https://ppid.bps.go.id/?mfd=0000)\n  * [Kebijakan Diseminasi](https://ppid.bps.go.id/app/konten/0000/Layanan-BPS.html#pills-3)\n\n\nTautan Lainnya\n  * [ASEAN Stats](https://www.aseanstats.org/)\n  * [Forum Masyarakat Statistik](https://fmsindonesia.id/)\n  * [Reformasi Birokrasi](https://rb.bps.go.id/)\n  * [Layanan Pengadaan Secara Elektronik](https://lpse.bps.go.id/)\n  * [Politeknik Statistika STIS](https://www.stis.ac.id/)\n  * [Pusdiklat BPS](https://pusdiklat.bps.go.id/)\n  * [JDIH BPS](https://jdih.bps.go.id/)\n\n\nHak Cipta © 2023 Badan Pusat Statistik\n[![](https://www.bps.go.id/assets/icons/twitter.svg)](https://www.twitter.com/bps_statistics)[![](https://www.bps.go.id/assets/icons/facebook.svg)](https://www.facebook.com/pages/Badan-Pusat-Statistik/1394866840805957)[![](https://www.bps.go.id/assets/icons/instagram.svg)](https://www.instagram.com/bps_statistics/)[![](https://www.bps.go.id/assets/icons/youtube.svg)](https://www.youtube.com/channel/UCn4IaaxHaaP-mAjZzrAtixA)\n",
  "content_hash": "cf29427faa160230",
  "word_count": 273,
  "scraped_at": "2025-10-07T22:25:49.171034",
  "language": "en",
  "links": [
    "internal",
    "external"
  ]
}